benchmarks/__init__.py
benchmarks/conftest.py
benchmarks/init_db.py
benchmarks/test_perf.py
profiler/__init__.py
profiler/__main__.py
pymerkle/__init__.py
pymerkle/constants.py
pymerkle/core.py
pymerkle/hasher.py
pymerkle/proof.py
pymerkle/utils.py
pymerkle/concrete/__init__.py
pymerkle/concrete/inmemory.py
pymerkle/concrete/sqlite.py
pymerkle-6.1.0.dist-info/LICENSE
pymerkle-6.1.0.dist-info/METADATA
pymerkle-6.1.0.dist-info/WHEEL
pymerkle-6.1.0.dist-info/top_level.txt
pymerkle-6.1.0.dist-info/RECORD
