Metadata-Version: 2.1
Name: pymerkle
Version: 6.1.0
Summary: Merkle-tree cryptography in python
Home-page: https://github.com/fmerg/pymerkle
Author: fmerg
Author-email: fmerg@protonmail.com
Project-URL: github, https://github.com/fmerg/pymerkle
Project-URL: source, https://github.com/fmerg/pymerkle/tree/master/pymerkle
Project-URL: docs, https://6.1.0.readthedocs.io/en/latest/
Keywords: merkle,proof,inclusion,consistency
Classifier: Development Status :: 4 - Beta
Classifier: Intended Audience :: Developers
Classifier: Intended Audience :: Science/Research
Classifier: Programming Language :: Python :: 3.6
Classifier: Operating System :: POSIX
Classifier: Topic :: Security :: Cryptography
Classifier: Topic :: Software Development :: Libraries :: Python Modules
Classifier: License :: OSI Approved :: GNU General Public License v3 or later (GPLv3+)
Requires-Python: >=3.6
License-File: LICENSE
